FileCreate/__init__.py
FileCreate/filecreate.py
tests/__init__.py
tests/test_FileCreate.py
filecreate-0.0.7.dist-info/LICENSE
filecreate-0.0.7.dist-info/METADATA
filecreate-0.0.7.dist-info/WHEEL
filecreate-0.0.7.dist-info/top_level.txt
filecreate-0.0.7.dist-info/RECORD
