Metadata-Version: 2.1
Name: filecreate
Version: 0.0.7
Summary: Provides functionality for creating a new empty file with unique name
Home-page: https://github.com/LuckyKarter/filecreate
Author: Egor Wexler
Author-email: egor.wexler@icloud.com
License: UNKNOWN
Project-URL: Bug Tracker, https://github.com/LuckyKarter/filecreate/issues
Platform: UNKNOWN
Classifier: Programming Language :: Python :: 3
Classifier: Intended Audience :: Developers
Classifier: License :: OSI Approved :: MIT License
Requires-Python: >=3.6
